boxhed/__init__.py
boxhed/boxhed.py
boxhed/model_selection.py
boxhed/utils.py
boxhed-2.0.13.dist-info/METADATA
boxhed-2.0.13.dist-info/WHEEL
boxhed-2.0.13.dist-info/top_level.txt
boxhed-2.0.13.dist-info/RECORD
