Metadata-Version: 2.4
Name: boxhed
Version: 2.0.13
Summary: BoXHED2.0
Author: Arash Pakbin, Bobak Mortazavi, and Donald K K Lee
Requires-Python: >=3.8
Requires-Dist: pandas
Requires-Dist: scikit-learn
Requires-Dist: matplotlib
Requires-Dist: tqdm
Requires-Dist: py3nvml
Requires-Dist: boxhed_kernel
Requires-Dist: boxhed_prep
Dynamic: author
Dynamic: description
Dynamic: description-content-type
Dynamic: requires-dist
Dynamic: requires-python
Dynamic: summary
